Flink17SnapshotZhongwenWendang/README.md
Flink17SnapshotZhongwenWendang/__init__.py
Flink17SnapshotZhongwenWendang/__main__.py
Flink17SnapshotZhongwenWendang/file.epub
Flink17SnapshotZhongwenWendang/index.html
Flink17SnapshotZhongwenWendang/css/__init__.py
Flink17SnapshotZhongwenWendang/css/annotations.css
Flink17SnapshotZhongwenWendang/css/main.css
Flink17SnapshotZhongwenWendang/css/normalize.css
Flink17SnapshotZhongwenWendang/css/popup.css
Flink17SnapshotZhongwenWendang/font/__init__.py
Flink17SnapshotZhongwenWendang/font/fontello.eot
Flink17SnapshotZhongwenWendang/font/fontello.svg
Flink17SnapshotZhongwenWendang/font/fontello.ttf
Flink17SnapshotZhongwenWendang/font/fontello.woff
Flink17SnapshotZhongwenWendang/img/__init__.py
Flink17SnapshotZhongwenWendang/img/annotator-glyph-sprite.png
Flink17SnapshotZhongwenWendang/img/annotator-icon-sprite.png
Flink17SnapshotZhongwenWendang/img/apple-touch-icon.png
Flink17SnapshotZhongwenWendang/img/cancelfullscreen.png
Flink17SnapshotZhongwenWendang/img/close.png
Flink17SnapshotZhongwenWendang/img/fullscreen.png
Flink17SnapshotZhongwenWendang/img/loader.gif
Flink17SnapshotZhongwenWendang/img/menu-icon.png
Flink17SnapshotZhongwenWendang/img/save.png
Flink17SnapshotZhongwenWendang/img/saved.png
Flink17SnapshotZhongwenWendang/img/settings-s.png
Flink17SnapshotZhongwenWendang/img/settings.png
Flink17SnapshotZhongwenWendang/img/star.png
Flink17SnapshotZhongwenWendang/js/__init__.py
Flink17SnapshotZhongwenWendang/js/epub.js
Flink17SnapshotZhongwenWendang/js/epub.min.js
Flink17SnapshotZhongwenWendang/js/epub.min.map
Flink17SnapshotZhongwenWendang/js/hooks.min.js
Flink17SnapshotZhongwenWendang/js/hooks.min.map
Flink17SnapshotZhongwenWendang/js/reader.js
Flink17SnapshotZhongwenWendang/js/reader.js.map
Flink17SnapshotZhongwenWendang/js/reader.min.js
Flink17SnapshotZhongwenWendang/js/reader.min.map
Flink17SnapshotZhongwenWendang/js/hooks/__init__.py
Flink17SnapshotZhongwenWendang/js/hooks/extensions/__init__.py
flink_1_7_snapshot_zhongwen_wendang-2024.3.4.0.dist-info/METADATA
flink_1_7_snapshot_zhongwen_wendang-2024.3.4.0.dist-info/WHEEL
flink_1_7_snapshot_zhongwen_wendang-2024.3.4.0.dist-info/entry_points.txt
flink_1_7_snapshot_zhongwen_wendang-2024.3.4.0.dist-info/top_level.txt
flink_1_7_snapshot_zhongwen_wendang-2024.3.4.0.dist-info/RECORD
